pyprob_distributions/Binomialdistribution.py
pyprob_distributions/Gaussiandistribution.py
pyprob_distributions/Generaldistribution.py
pyprob_distributions/__init__.py
pyprob_distributions-0.2.dist-info/METADATA
pyprob_distributions-0.2.dist-info/WHEEL
pyprob_distributions-0.2.dist-info/top_level.txt
pyprob_distributions-0.2.dist-info/RECORD
