Metadata-Version: 2.1
Name: pyprob-distributions
Version: 0.2
Summary: Gaussian and Binominal distributions
Home-page: https://github.com/AdithyaYelloju/pyprob-distributions
Author: Adithya Yelloju
Author-email: adithyayelloju@gmail.com
License: UNKNOWN
Platform: UNKNOWN
